pyaquarite/__init__.py
pyaquarite/api.py
pyaquarite/auth.py
pyaquarite/coordinator.py
pyaquarite/exceptions.py
pyaquarite-1.0.8.dist-info/METADATA
pyaquarite-1.0.8.dist-info/WHEEL
pyaquarite-1.0.8.dist-info/top_level.txt
pyaquarite-1.0.8.dist-info/RECORD
