Metadata-Version: 2.4
Name: pyaquarite
Version: 1.0.8
Summary: Aquarite Python API Client
Home-page: https://github.com/yourusername/pyaquarite
Author: Your Name
Classifier: Programming Language :: Python :: 3
Classifier: License :: OSI Approved :: MIT License
Classifier: Operating System :: OS Independent
Requires-Python: >=3.9
Requires-Dist: aiohttp
Requires-Dist: google-cloud-firestore
Requires-Dist: google-auth
Dynamic: author
Dynamic: classifier
Dynamic: home-page
Dynamic: requires-dist
Dynamic: requires-python
Dynamic: summary
